[{"Country": "Guinea-Bissau", "Confirmed": 2, "Deaths": 0, "Recovered": 0, "Active": 2, "Date": "2020-03-25T00:00:00Z", "ISO": "GW", "Geometry": [[-16.0, 12.0], [-15.0, 11.0], [-15.0, 12.0], [-14.0, 12.0]]}, {"Country": "Guinea-Bissau", "Confirmed": 2, "Deaths": 0, "Recovered": 0, "Active": 2, "Date": "2020-03-26T00:00:00Z", "ISO": "GW", "Geometry": [[-16.0, 12.0], [-15.0, 11.0], [-15.0, 12.0], [-14.0, 12.0]]}, {"Country": "Guinea-Bissau", "Confirmed": 2, "Deaths": 0, "Recovered": 0, "Active": 2, "Date": "2020-03-27T00:00:00Z", "ISO": "GW", "Geometry": [[-16.0, 12.0], [-15.0, 11.0], [-15.0, 12.0], [-14.0, 12.0]]}, {"Country": "Guinea-Bissau", "Confirmed": 2, "Deaths": 0, "Recovered": 0, "Active": 2, "Date": "2020-03-28T00:00:00Z", "ISO": "GW", "Geometry": [[-16.0, 12.0], [-15.0, 11.0], [-15.0, 12.0], [-14.0, 12.0]]}, {"Country": "Guinea-Bissau", "Confirmed": 2, "Deaths": 0, "Recovered": 0, "Active": 2, "Date": "2020-03-29T00:00:00Z", "ISO": "GW", "Geometry": [[-16.0, 12.0], [-15.0, 11.0], [-15.0, 12.0], [-14.0, 12.0]]}, {"Country": "Guinea-Bissau", "Confirmed": 8, "Deaths": 0, "Recovered": 0, "Active": 8, "Date": "2020-03-30T00:00:00Z", "ISO": "GW", "Geometry": [[-16.0, 12.0], [-15.0, 11.0], [-15.0, 12.0], [-14.0, 12.0]]}, {"Country": "Guinea-Bissau", "Confirmed": 8, "Deaths": 0, "Recovered": 0, "Active": 8, "Date": "2020-03-31T00:00:00Z", "ISO": "GW", "Geometry": [[-16.0, 12.0], [-15.0, 11.0], [-15.0, 12.0], [-14.0, 12.0]]}, {"Country": "Guinea-Bissau", "Confirmed": 9, "Deaths": 0, "Recovered": 0, "Active": 9, "Date": "2020-04-01T00:00:00Z", "ISO": "GW", "Geometry": [[-16.0, 12.0], [-15.0, 11.0], [-15.0, 12.0], [-14.0, 12.0]]}, {"Country": "Guinea-Bissau", "Confirmed": 9, "Deaths": 0, "Recovered": 0, "Active": 9, "Date": "2020-04-02T00:00:00Z", "ISO": "GW", "Geometry": [[-16.0, 12.0], [-15.0, 11.0], [-15.0, 12.0], [-14.0, 12.0]]}, {"Country": "Guinea-Bissau", "Confirmed": 15, "Deaths": 0, "Recovered": 0, "Active": 15, "Date": "2020-04-03T00:00:00Z", "ISO": "GW", "Geometry": [[-16.0, 12.0], [-15.0, 11.0], [-15.0, 12.0], [-14.0, 12.0]]}, {"Country": "Guinea-Bissau", "Confirmed": 18, "Deaths": 0, "Recovered": 0, "Active": 18, "Date": "2020-04-04T00:00:00Z", "ISO": "GW", "Geometry": [[-16.0, 12.0], [-15.0, 11.0], [-15.0, 12.0], [-14.0, 12.0]]}, {"Country": "Guinea-Bissau", "Confirmed": 18, "Deaths": 0, "Recovered": 0, "Active": 18, "Date": "2020-04-05T00:00:00Z", "ISO": "GW", "Geometry": [[-16.0, 12.0], [-15.0, 11.0], [-15.0, 12.0], [-14.0, 12.0]]}, {"Country": "Guinea-Bissau", "Confirmed": 18, "Deaths": 0, "Recovered": 0, "Active": 18, "Date": "2020-04-06T00:00:00Z", "ISO": "GW", "Geometry": [[-16.0, 12.0], [-15.0, 11.0], [-15.0, 12.0], [-14.0, 12.0]]}, {"Country": "Guinea-Bissau", "Confirmed": 33, "Deaths": 0, "Recovered": 0, "Active": 33, "Date": "2020-04-07T00:00:00Z", "ISO": "GW", "Geometry": [[-16.0, 12.0], [-15.0, 11.0], [-15.0, 12.0], [-14.0, 12.0]]}, {"Country": "Guinea-Bissau", "Confirmed": 33, "Deaths": 0, "Recovered": 0, "Active": 33, "Date": "2020-04-08T00:00:00Z", "ISO": "GW", "Geometry": [[-16.0, 12.0], [-15.0, 11.0], [-15.0, 12.0], [-14.0, 12.0]]}, {"Country": "Guinea-Bissau", "Confirmed": 36, "Deaths": 0, "Recovered": 0, "Active": 36, "Date": "2020-04-09T00:00:00Z", "ISO": "GW", "Geometry": [[-16.0, 12.0], [-15.0, 11.0], [-15.0, 12.0], [-14.0, 12.0]]}, {"Country": "Guinea-Bissau", "Confirmed": 36, "Deaths": 0, "Recovered": 0, "Active": 36, "Date": "2020-04-10T00:00:00Z", "ISO": "GW", "Geometry": [[-16.0, 12.0], [-15.0, 11.0], [-15.0, 12.0], [-14.0, 12.0]]}, {"Country": "Guinea-Bissau", "Confirmed": 38, "Deaths": 0, "Recovered": 0, "Active": 38, "Date": "2020-04-11T00:00:00Z", "ISO": "GW", "Geometry": [[-16.0, 12.0], [-15.0, 11.0], [-15.0, 12.0], [-14.0, 12.0]]}, {"Country": "Guinea-Bissau", "Confirmed": 38, "Deaths": 0, "Recovered": 0, "Active": 38, "Date": "2020-04-12T00:00:00Z", "ISO": "GW", "Geometry": [[-16.0, 12.0], [-15.0, 11.0], [-15.0, 12.0], [-14.0, 12.0]]}, {"Country": "Guinea-Bissau", "Confirmed": 38, "Deaths": 0, "Recovered": 0, "Active": 38, "Date": "2020-04-13T00:00:00Z", "ISO": "GW", "Geometry": [[-16.0, 12.0], [-15.0, 11.0], [-15.0, 12.0], [-14.0, 12.0]]}, {"Country": "Guinea-Bissau", "Confirmed": 38, "Deaths": 0, "Recovered": 0, "Active": 38, "Date": "2020-04-14T00:00:00Z", "ISO": "GW", "Geometry": [[-16.0, 12.0], [-15.0, 11.0], [-15.0, 12.0], [-14.0, 12.0]]}, {"Country": "Guinea-Bissau", "Confirmed": 43, "Deaths": 0, "Recovered": 0, "Active": 43, "Date": "2020-04-15T00:00:00Z", "ISO": "GW", "Geometry": [[-16.0, 12.0], [-15.0, 11.0], [-15.0, 12.0], [-14.0, 12.0]]}, {"Country": "Guinea-Bissau", "Confirmed": 43, "Deaths": 0, "Recovered": 0, "Active": 43, "Date": "2020-04-16T00:00:00Z", "ISO": "GW", "Geometry": [[-16.0, 12.0], [-15.0, 11.0], [-15.0, 12.0], [-14.0, 12.0]]}, {"Country": "Guinea-Bissau", "Confirmed": 43, "Deaths": 0, "Recovered": 0, "Active": 43, "Date": "2020-04-17T00:00:00Z", "ISO": "GW", "Geometry": [[-16.0, 12.0], [-15.0, 11.0], [-15.0, 12.0], [-14.0, 12.0]]}, {"Country": "Guinea-Bissau", "Confirmed": 46, "Deaths": 0, "Recovered": 0, "Active": 46, "Date": "2020-04-18T00:00:00Z", "ISO": "GW", "Geometry": [[-16.0, 12.0], [-15.0, 11.0], [-15.0, 12.0], [-14.0, 12.0]]}, {"Country": "Guinea-Bissau", "Confirmed": 50, "Deaths": 0, "Recovered": 3, "Active": 47, "Date": "2020-04-19T00:00:00Z", "ISO": "GW", "Geometry": [[-16.0, 12.0], [-15.0, 11.0], [-15.0, 12.0], [-14.0, 12.0]]}, {"Country": "Guinea-Bissau", "Confirmed": 50, "Deaths": 0, "Recovered": 3, "Active": 47, "Date": "2020-04-20T00:00:00Z", "ISO": "GW", "Geometry": [[-16.0, 12.0], [-15.0, 11.0], [-15.0, 12.0], [-14.0, 12.0]]}, {"Country": "Guinea-Bissau", "Confirmed": 50, "Deaths": 0, "Recovered": 3, "Active": 47, "Date": "2020-04-21T00:00:00Z", "ISO": "GW", "Geometry": [[-16.0, 12.0], [-15.0, 11.0], [-15.0, 12.0], [-14.0, 12.0]]}, {"Country": "Guinea-Bissau", "Confirmed": 50, "Deaths": 0, "Recovered": 3, "Active": 47, "Date": "2020-04-22T00:00:00Z", "ISO": "GW", "Geometry": [[-16.0, 12.0], [-15.0, 11.0], [-15.0, 12.0], [-14.0, 12.0]]}, {"Country": "Guinea-Bissau", "Confirmed": 50, "Deaths": 0, "Recovered": 3, "Active": 47, "Date": "2020-04-23T00:00:00Z", "ISO": "GW", "Geometry": [[-16.0, 12.0], [-15.0, 11.0], [-15.0, 12.0], [-14.0, 12.0]]}, {"Country": "Guinea-Bissau", "Confirmed": 52, "Deaths": 0, "Recovered": 3, "Active": 49, "Date": "2020-04-24T00:00:00Z", "ISO": "GW", "Geometry": [[-16.0, 12.0], [-15.0, 11.0], [-15.0, 12.0], [-14.0, 12.0]]}, {"Country": "Guinea-Bissau", "Confirmed": 52, "Deaths": 0, "Recovered": 3, "Active": 49, "Date": "2020-04-25T00:00:00Z", "ISO": "GW", "Geometry": [[-16.0, 12.0], [-15.0, 11.0], [-15.0, 12.0], [-14.0, 12.0]]}, {"Country": "Guinea-Bissau", "Confirmed": 53, "Deaths": 1, "Recovered": 3, "Active": 49, "Date": "2020-04-26T00:00:00Z", "ISO": "GW", "Geometry": [[-16.0, 12.0], [-15.0, 11.0], [-15.0, 12.0], [-14.0, 12.0]]}, {"Country": "Guinea-Bissau", "Confirmed": 73, "Deaths": 1, "Recovered": 18, "Active": 54, "Date": "2020-04-27T00:00:00Z", "ISO": "GW", "Geometry": [[-16.0, 12.0], [-15.0, 11.0], [-15.0, 12.0], [-14.0, 12.0]]}, {"Country": "Guinea-Bissau", "Confirmed": 73, "Deaths": 1, "Recovered": 18, "Active": 54, "Date": "2020-04-28T00:00:00Z", "ISO": "GW", "Geometry": [[-16.0, 12.0], [-15.0, 11.0], [-15.0, 12.0], [-14.0, 12.0]]}, {"Country": "Guinea-Bissau", "Confirmed": 205, "Deaths": 1, "Recovered": 19, "Active": 185, "Date": "2020-04-29T00:00:00Z", "ISO": "GW", "Geometry": [[-16.0, 12.0], [-15.0, 11.0], [-15.0, 12.0], [-14.0, 12.0]]}, {"Country": "Guinea-Bissau", "Confirmed": 205, "Deaths": 1, "Recovered": 19, "Active": 185, "Date": "2020-04-30T00:00:00Z", "ISO": "GW", "Geometry": [[-16.0, 12.0], [-15.0, 11.0], [-15.0, 12.0], [-14.0, 12.0]]}, {"Country": "Guinea-Bissau", "Confirmed": 257, "Deaths": 1, "Recovered": 19, "Active": 237, "Date": "2020-05-01T00:00:00Z", "ISO": "GW", "Geometry": [[-16.0, 12.0], [-15.0, 11.0], [-15.0, 12.0], [-14.0, 12.0]]}, {"Country": "Guinea-Bissau", "Confirmed": 257, "Deaths": 1, "Recovered": 19, "Active": 237, "Date": "2020-05-02T00:00:00Z", "ISO": "GW", "Geometry": [[-16.0, 12.0], [-15.0, 11.0], [-15.0, 12.0], [-14.0, 12.0]]}, {"Country": "Guinea-Bissau", "Confirmed": 257, "Deaths": 1, "Recovered": 19, "Active": 237, "Date": "2020-05-03T00:00:00Z", "ISO": "GW", "Geometry": [[-16.0, 12.0], [-15.0, 11.0], [-15.0, 12.0], [-14.0, 12.0]]}, {"Country": "Guinea-Bissau", "Confirmed": 413, "Deaths": 1, "Recovered": 19, "Active": 393, "Date": "2020-05-04T00:00:00Z", "ISO": "GW", "Geometry": [[-16.0, 12.0], [-15.0, 11.0], [-15.0, 12.0], [-14.0, 12.0]]}, {"Country": "Guinea-Bissau", "Confirmed": 413, "Deaths": 1, "Recovered": 19, "Active": 393, "Date": "2020-05-05T00:00:00Z", "ISO": "GW", "Geometry": [[-16.0, 12.0], [-15.0, 11.0], [-15.0, 12.0], [-14.0, 12.0]]}, {"Country": "Guinea-Bissau", "Confirmed": 475, "Deaths": 2, "Recovered": 24, "Active": 449, "Date": "2020-05-06T00:00:00Z", "ISO": "GW", "Geometry": [[-16.0, 12.0], [-15.0, 11.0], [-15.0, 12.0], [-14.0, 12.0]]}, {"Country": "Guinea-Bissau", "Confirmed": 564, "Deaths": 2, "Recovered": 25, "Active": 537, "Date": "2020-05-07T00:00:00Z", "ISO": "GW", "Geometry": [[-16.0, 12.0], [-15.0, 11.0], [-15.0, 12.0], [-14.0, 12.0]]}, {"Country": "Guinea-Bissau", "Confirmed": 594, "Deaths": 2, "Recovered": 25, "Active": 567, "Date": "2020-05-08T00:00:00Z", "ISO": "GW", "Geometry": [[-16.0, 12.0], [-15.0, 11.0], [-15.0, 12.0], [-14.0, 12.0]]}, {"Country": "Guinea-Bissau", "Confirmed": 641, "Deaths": 3, "Recovered": 25, "Active": 613, "Date": "2020-05-09T00:00:00Z", "ISO": "GW", "Geometry": [[-16.0, 12.0], [-15.0, 11.0], [-15.0, 12.0], [-14.0, 12.0]]}, {"Country": "Guinea-Bissau", "Confirmed": 726, "Deaths": 3, "Recovered": 26, "Active": 697, "Date": "2020-05-10T00:00:00Z", "ISO": "GW", "Geometry": [[-16.0, 12.0], [-15.0, 11.0], [-15.0, 12.0], [-14.0, 12.0]]}, {"Country": "Guinea-Bissau", "Confirmed": 761, "Deaths": 3, "Recovered": 26, "Active": 732, "Date": "2020-05-11T00:00:00Z", "ISO": "GW", "Geometry": [[-16.0, 12.0], [-15.0, 11.0], [-15.0, 12.0], [-14.0, 12.0]]}, {"Country": "Guinea-Bissau", "Confirmed": 820, "Deaths": 3, "Recovered": 26, "Active": 791, "Date": "2020-05-12T00:00:00Z", "ISO": "GW", "Geometry": [[-16.0, 12.0], [-15.0, 11.0], [-15.0, 12.0], [-14.0, 12.0]]}, {"Country": "Guinea-Bissau", "Confirmed": 836, "Deaths": 3, "Recovered": 26, "Active": 807, "Date": "2020-05-13T00:00:00Z", "ISO": "GW", "Geometry": [[-16.0, 12.0], [-15.0, 11.0], [-15.0, 12.0], [-14.0, 12.0]]}, {"Country": "Guinea-Bissau", "Confirmed": 913, "Deaths": 3, "Recovered": 26, "Active": 884, "Date": "2020-05-14T00:00:00Z", "ISO": "GW", "Geometry": [[-16.0, 12.0], [-15.0, 11.0], [-15.0, 12.0], [-14.0, 12.0]]}, {"Country": "Guinea-Bissau", "Confirmed": 913, "Deaths": 3, "Recovered": 26, "Active": 884, "Date": "2020-05-15T00:00:00Z", "ISO": "GW", "Geometry": [[-16.0, 12.0], [-15.0, 11.0], [-15.0, 12.0], [-14.0, 12.0]]}, {"Country": "Guinea-Bissau", "Confirmed": 969, "Deaths": 4, "Recovered": 26, "Active": 939, "Date": "2020-05-16T00:00:00Z", "ISO": "GW", "Geometry": [[-16.0, 12.0], [-15.0, 11.0], [-15.0, 12.0], [-14.0, 12.0]]}, {"Country": "Guinea-Bissau", "Confirmed": 990, "Deaths": 4, "Recovered": 26, "Active": 960, "Date": "2020-05-17T00:00:00Z", "ISO": "GW", "Geometry": [[-16.0, 12.0], [-15.0, 11.0], [-15.0, 12.0], [-14.0, 12.0]]}, {"Country": "Guinea-Bissau", "Confirmed": 1032, "Deaths": 4, "Recovered": 38, "Active": 990, "Date": "2020-05-18T00:00:00Z", "ISO": "GW", "Geometry": [[-16.0, 12.0], [-15.0, 11.0], [-15.0, 12.0], [-14.0, 12.0]]}, {"Country": "Guinea-Bissau", "Confirmed": 1038, "Deaths": 6, "Recovered": 42, "Active": 990, "Date": "2020-05-19T00:00:00Z", "ISO": "GW", "Geometry": [[-16.0, 12.0], [-15.0, 11.0], [-15.0, 12.0], [-14.0, 12.0]]}, {"Country": "Guinea-Bissau", "Confirmed": 1089, "Deaths": 6, "Recovered": 42, "Active": 1041, "Date": "2020-05-20T00:00:00Z", "ISO": "GW", "Geometry": [[-16.0, 12.0], [-15.0, 11.0], [-15.0, 12.0], [-14.0, 12.0]]}, {"Country": "Guinea-Bissau", "Confirmed": 1109, "Deaths": 6, "Recovered": 42, "Active": 1061, "Date": "2020-05-21T00:00:00Z", "ISO": "GW", "Geometry": [[-16.0, 12.0], [-15.0, 11.0], [-15.0, 12.0], [-14.0, 12.0]]}, {"Country": "Guinea-Bissau", "Confirmed": 1114, "Deaths": 6, "Recovered": 42, "Active": 1066, "Date": "2020-05-22T00:00:00Z", "ISO": "GW", "Geometry": [[-16.0, 12.0], [-15.0, 11.0], [-15.0, 12.0], [-14.0, 12.0]]}, {"Country": "Guinea-Bissau", "Confirmed": 1114, "Deaths": 6, "Recovered": 42, "Active": 1066, "Date": "2020-05-23T00:00:00Z", "ISO": "GW", "Geometry": [[-16.0, 12.0], [-15.0, 11.0], [-15.0, 12.0], [-14.0, 12.0]]}, {"Country": "Guinea-Bissau", "Confirmed": 1114, "Deaths": 6, "Recovered": 42, "Active": 1066, "Date": "2020-05-24T00:00:00Z", "ISO": "GW", "Geometry": [[-16.0, 12.0], [-15.0, 11.0], [-15.0, 12.0], [-14.0, 12.0]]}, {"Country": "Guinea-Bissau", "Confirmed": 1178, "Deaths": 7, "Recovered": 42, "Active": 1129, "Date": "2020-05-25T00:00:00Z", "ISO": "GW", "Geometry": [[-16.0, 12.0], [-15.0, 11.0], [-15.0, 12.0], [-14.0, 12.0]]}, {"Country": "Guinea-Bissau", "Confirmed": 1178, "Deaths": 7, "Recovered": 42, "Active": 1129, "Date": "2020-05-26T00:00:00Z", "ISO": "GW", "Geometry": [[-16.0, 12.0], [-15.0, 11.0], [-15.0, 12.0], [-14.0, 12.0]]}, {"Country": "Guinea-Bissau", "Confirmed": 1195, "Deaths": 7, "Recovered": 42, "Active": 1146, "Date": "2020-05-27T00:00:00Z", "ISO": "GW", "Geometry": [[-16.0, 12.0], [-15.0, 11.0], [-15.0, 12.0], [-14.0, 12.0]]}, {"Country": "Guinea-Bissau", "Confirmed": 1195, "Deaths": 8, "Recovered": 42, "Active": 1145, "Date": "2020-05-28T00:00:00Z", "ISO": "GW", "Geometry": [[-16.0, 12.0], [-15.0, 11.0], [-15.0, 12.0], [-14.0, 12.0]]}, {"Country": "Guinea-Bissau", "Confirmed": 1256, "Deaths": 8, "Recovered": 42, "Active": 1206, "Date": "2020-05-29T00:00:00Z", "ISO": "GW", "Geometry": [[-16.0, 12.0], [-15.0, 11.0], [-15.0, 12.0], [-14.0, 12.0]]}, {"Country": "Guinea-Bissau", "Confirmed": 1256, "Deaths": 8, "Recovered": 42, "Active": 1206, "Date": "2020-05-30T00:00:00Z", "ISO": "GW", "Geometry": [[-16.0, 12.0], [-15.0, 11.0], [-15.0, 12.0], [-14.0, 12.0]]}, {"Country": "Guinea-Bissau", "Confirmed": 1256, "Deaths": 8, "Recovered": 42, "Active": 1206, "Date": "2020-05-31T00:00:00Z", "ISO": "GW", "Geometry": [[-16.0, 12.0], [-15.0, 11.0], [-15.0, 12.0], [-14.0, 12.0]]}, {"Country": "Guinea-Bissau", "Confirmed": 1339, "Deaths": 8, "Recovered": 53, "Active": 1278, "Date": "2020-06-01T00:00:00Z", "ISO": "GW", "Geometry": [[-16.0, 12.0], [-15.0, 11.0], [-15.0, 12.0], [-14.0, 12.0]]}, {"Country": "Guinea-Bissau", "Confirmed": 1339, "Deaths": 8, "Recovered": 53, "Active": 1278, "Date": "2020-06-02T00:00:00Z", "ISO": "GW", "Geometry": [[-16.0, 12.0], [-15.0, 11.0], [-15.0, 12.0], [-14.0, 12.0]]}, {"Country": "Guinea-Bissau", "Confirmed": 1339, "Deaths": 8, "Recovered": 53, "Active": 1278, "Date": "2020-06-03T00:00:00Z", "ISO": "GW", "Geometry": [[-16.0, 12.0], [-15.0, 11.0], [-15.0, 12.0], [-14.0, 12.0]]}, {"Country": "Guinea-Bissau", "Confirmed": 1339, "Deaths": 8, "Recovered": 53, "Active": 1278, "Date": "2020-06-04T00:00:00Z", "ISO": "GW", "Geometry": [[-16.0, 12.0], [-15.0, 11.0], [-15.0, 12.0], [-14.0, 12.0]]}, {"Country": "Guinea-Bissau", "Confirmed": 1368, "Deaths": 12, "Recovered": 153, "Active": 1203, "Date": "2020-06-05T00:00:00Z", "ISO": "GW", "Geometry": [[-16.0, 12.0], [-15.0, 11.0], [-15.0, 12.0], [-14.0, 12.0]]}, {"Country": "Guinea-Bissau", "Confirmed": 1368, "Deaths": 12, "Recovered": 153, "Active": 1203, "Date": "2020-06-06T00:00:00Z", "ISO": "GW", "Geometry": [[-16.0, 12.0], [-15.0, 11.0], [-15.0, 12.0], [-14.0, 12.0]]}, {"Country": "Guinea-Bissau", "Confirmed": 1368, "Deaths": 12, "Recovered": 153, "Active": 1203, "Date": "2020-06-07T00:00:00Z", "ISO": "GW", "Geometry": [[-16.0, 12.0], [-15.0, 11.0], [-15.0, 12.0], [-14.0, 12.0]]}, {"Country": "Guinea-Bissau", "Confirmed": 1389, "Deaths": 12, "Recovered": 153, "Active": 1224, "Date": "2020-06-08T00:00:00Z", "ISO": "GW", "Geometry": [[-16.0, 12.0], [-15.0, 11.0], [-15.0, 12.0], [-14.0, 12.0]]}, {"Country": "Guinea-Bissau", "Confirmed": 1389, "Deaths": 12, "Recovered": 153, "Active": 1224, "Date": "2020-06-09T00:00:00Z", "ISO": "GW", "Geometry": [[-16.0, 12.0], [-15.0, 11.0], [-15.0, 12.0], [-14.0, 12.0]]}, {"Country": "Guinea-Bissau", "Confirmed": 1389, "Deaths": 12, "Recovered": 153, "Active": 1224, "Date": "2020-06-10T00:00:00Z", "ISO": "GW", "Geometry": [[-16.0, 12.0], [-15.0, 11.0], [-15.0, 12.0], [-14.0, 12.0]]}, {"Country": "Guinea-Bissau", "Confirmed": 1389, "Deaths": 12, "Recovered": 153, "Active": 1224, "Date": "2020-06-11T00:00:00Z", "ISO": "GW", "Geometry": [[-16.0, 12.0], [-15.0, 11.0], [-15.0, 12.0], [-14.0, 12.0]]}, {"Country": "Guinea-Bissau", "Confirmed": 1460, "Deaths": 15, "Recovered": 153, "Active": 1292, "Date": "2020-06-12T00:00:00Z", "ISO": "GW", "Geometry": [[-16.0, 12.0], [-15.0, 11.0], [-15.0, 12.0], [-14.0, 12.0]]}, {"Country": "Guinea-Bissau", "Confirmed": 1460, "Deaths": 15, "Recovered": 153, "Active": 1292, "Date": "2020-06-13T00:00:00Z", "ISO": "GW", "Geometry": [[-16.0, 12.0], [-15.0, 11.0], [-15.0, 12.0], [-14.0, 12.0]]}, {"Country": "Guinea-Bissau", "Confirmed": 1460, "Deaths": 15, "Recovered": 153, "Active": 1292, "Date": "2020-06-14T00:00:00Z", "ISO": "GW", "Geometry": [[-16.0, 12.0], [-15.0, 11.0], [-15.0, 12.0], [-14.0, 12.0]]}, {"Country": "Guinea-Bissau", "Confirmed": 1492, "Deaths": 15, "Recovered": 153, "Active": 1324, "Date": "2020-06-15T00:00:00Z", "ISO": "GW", "Geometry": [[-16.0, 12.0], [-15.0, 11.0], [-15.0, 12.0], [-14.0, 12.0]]}, {"Country": "Guinea-Bissau", "Confirmed": 1492, "Deaths": 15, "Recovered": 153, "Active": 1324, "Date": "2020-06-16T00:00:00Z", "ISO": "GW", "Geometry": [[-16.0, 12.0], [-15.0, 11.0], [-15.0, 12.0], [-14.0, 12.0]]}, {"Country": "Guinea-Bissau", "Confirmed": 1492, "Deaths": 15, "Recovered": 153, "Active": 1324, "Date": "2020-06-17T00:00:00Z", "ISO": "GW", "Geometry": [[-16.0, 12.0], [-15.0, 11.0], [-15.0, 12.0], [-14.0, 12.0]]}, {"Country": "Guinea-Bissau", "Confirmed": 1492, "Deaths": 15, "Recovered": 153, "Active": 1324, "Date": "2020-06-18T00:00:00Z", "ISO": "GW", "Geometry": [[-16.0, 12.0], [-15.0, 11.0], [-15.0, 12.0], [-14.0, 12.0]]}, {"Country": "Guinea-Bissau", "Confirmed": 1541, "Deaths": 17, "Recovered": 153, "Active": 1371, "Date": "2020-06-19T00:00:00Z", "ISO": "GW", "Geometry": [[-16.0, 12.0], [-15.0, 11.0], [-15.0, 12.0], [-14.0, 12.0]]}, {"Country": "Guinea-Bissau", "Confirmed": 1541, "Deaths": 17, "Recovered": 153, "Active": 1371, "Date": "2020-06-20T00:00:00Z", "ISO": "GW", "Geometry": [[-16.0, 12.0], [-15.0, 11.0], [-15.0, 12.0], [-14.0, 12.0]]}, {"Country": "Guinea-Bissau", "Confirmed": 1541, "Deaths": 17, "Recovered": 153, "Active": 1371, "Date": "2020-06-21T00:00:00Z", "ISO": "GW", "Geometry": [[-16.0, 12.0], [-15.0, 11.0], [-15.0, 12.0], [-14.0, 12.0]]}, {"Country": "Guinea-Bissau", "Confirmed": 1556, "Deaths": 19, "Recovered": 191, "Active": 1346, "Date": "2020-06-22T00:00:00Z", "ISO": "GW", "Geometry": [[-16.0, 12.0], [-15.0, 11.0], [-15.0, 12.0], [-14.0, 12.0]]}, {"Country": "Guinea-Bissau", "Confirmed": 1556, "Deaths": 19, "Recovered": 191, "Active": 1346, "Date": "2020-06-23T00:00:00Z", "ISO": "GW", "Geometry": [[-16.0, 12.0], [-15.0, 11.0], [-15.0, 12.0], [-14.0, 12.0]]}, {"Country": "Guinea-Bissau", "Confirmed": 1556, "Deaths": 19, "Recovered": 191, "Active": 1346, "Date": "2020-06-24T00:00:00Z", "ISO": "GW", "Geometry": [[-16.0, 12.0], [-15.0, 11.0], [-15.0, 12.0], [-14.0, 12.0]]}, {"Country": "Guinea-Bissau", "Confirmed": 1556, "Deaths": 19, "Recovered": 191, "Active": 1346, "Date": "2020-06-25T00:00:00Z", "ISO": "GW", "Geometry": [[-16.0, 12.0], [-15.0, 11.0], [-15.0, 12.0], [-14.0, 12.0]]}, {"Country": "Guinea-Bissau", "Confirmed": 1614, "Deaths": 22, "Recovered": 191, "Active": 1401, "Date": "2020-06-26T00:00:00Z", "ISO": "GW", "Geometry": [[-16.0, 12.0], [-15.0, 11.0], [-15.0, 12.0], [-14.0, 12.0]]}, {"Country": "Guinea-Bissau", "Confirmed": 1614, "Deaths": 22, "Recovered": 317, "Active": 1275, "Date": "2020-06-27T00:00:00Z", "ISO": "GW", "Geometry": [[-16.0, 12.0], [-15.0, 11.0], [-15.0, 12.0], [-14.0, 12.0]]}, {"Country": "Guinea-Bissau", "Confirmed": 1614, "Deaths": 22, "Recovered": 317, "Active": 1275, "Date": "2020-06-28T00:00:00Z", "ISO": "GW", "Geometry": [[-16.0, 12.0], [-15.0, 11.0], [-15.0, 12.0], [-14.0, 12.0]]}, {"Country": "Guinea-Bissau", "Confirmed": 1654, "Deaths": 24, "Recovered": 317, "Active": 1313, "Date": "2020-06-29T00:00:00Z", "ISO": "GW", "Geometry": [[-16.0, 12.0], [-15.0, 11.0], [-15.0, 12.0], [-14.0, 12.0]]}, {"Country": "Guinea-Bissau", "Confirmed": 1654, "Deaths": 24, "Recovered": 317, "Active": 1313, "Date": "2020-06-30T00:00:00Z", "ISO": "GW", "Geometry": [[-16.0, 12.0], [-15.0, 11.0], [-15.0, 12.0], [-14.0, 12.0]]}, {"Country": "Guinea-Bissau", "Confirmed": 1654, "Deaths": 24, "Recovered": 317, "Active": 1313, "Date": "2020-07-01T00:00:00Z", "ISO": "GW", "Geometry": [[-16.0, 12.0], [-15.0, 11.0], [-15.0, 12.0], [-14.0, 12.0]]}, {"Country": "Guinea-Bissau", "Confirmed": 1654, "Deaths": 24, "Recovered": 317, "Active": 1313, "Date": "2020-07-02T00:00:00Z", "ISO": "GW", "Geometry": [[-16.0, 12.0], [-15.0, 11.0], [-15.0, 12.0], [-14.0, 12.0]]}, {"Country": "Guinea-Bissau", "Confirmed": 1765, "Deaths": 25, "Recovered": 676, "Active": 1064, "Date": "2020-07-03T00:00:00Z", "ISO": "GW", "Geometry": [[-16.0, 12.0], [-15.0, 11.0], [-15.0, 12.0], [-14.0, 12.0]]}, {"Country": "Guinea-Bissau", "Confirmed": 1765, "Deaths": 25, "Recovered": 676, "Active": 1064, "Date": "2020-07-04T00:00:00Z", "ISO": "GW", "Geometry": [[-16.0, 12.0], [-15.0, 11.0], [-15.0, 12.0], [-14.0, 12.0]]}, {"Country": "Guinea-Bissau", "Confirmed": 1765, "Deaths": 25, "Recovered": 676, "Active": 1064, "Date": "2020-07-05T00:00:00Z", "ISO": "GW", "Geometry": [[-16.0, 12.0], [-15.0, 11.0], [-15.0, 12.0], [-14.0, 12.0]]}, {"Country": "Guinea-Bissau", "Confirmed": 1790, "Deaths": 25, "Recovered": 760, "Active": 1005, "Date": "2020-07-06T00:00:00Z", "ISO": "GW", "Geometry": [[-16.0, 12.0], [-15.0, 11.0], [-15.0, 12.0], [-14.0, 12.0]]}, {"Country": "Guinea-Bissau", "Confirmed": 1790, "Deaths": 25, "Recovered": 760, "Active": 1005, "Date": "2020-07-07T00:00:00Z", "ISO": "GW", "Geometry": [[-16.0, 12.0], [-15.0, 11.0], [-15.0, 12.0], [-14.0, 12.0]]}, {"Country": "Guinea-Bissau", "Confirmed": 1790, "Deaths": 25, "Recovered": 760, "Active": 1005, "Date": "2020-07-08T00:00:00Z", "ISO": "GW", "Geometry": [[-16.0, 12.0], [-15.0, 11.0], [-15.0, 12.0], [-14.0, 12.0]]}, {"Country": "Guinea-Bissau", "Confirmed": 1790, "Deaths": 25, "Recovered": 760, "Active": 1005, "Date": "2020-07-09T00:00:00Z", "ISO": "GW", "Geometry": [[-16.0, 12.0], [-15.0, 11.0], [-15.0, 12.0], [-14.0, 12.0]]}, {"Country": "Guinea-Bissau", "Confirmed": 1842, "Deaths": 26, "Recovered": 773, "Active": 1043, "Date": "2020-07-10T00:00:00Z", "ISO": "GW", "Geometry": [[-16.0, 12.0], [-15.0, 11.0], [-15.0, 12.0], [-14.0, 12.0]]}, {"Country": "Guinea-Bissau", "Confirmed": 1842, "Deaths": 26, "Recovered": 773, "Active": 1043, "Date": "2020-07-11T00:00:00Z", "ISO": "GW", "Geometry": [[-16.0, 12.0], [-15.0, 11.0], [-15.0, 12.0], [-14.0, 12.0]]}, {"Country": "Guinea-Bissau", "Confirmed": 1842, "Deaths": 26, "Recovered": 773, "Active": 1043, "Date": "2020-07-12T00:00:00Z", "ISO": "GW", "Geometry": [[-16.0, 12.0], [-15.0, 11.0], [-15.0, 12.0], [-14.0, 12.0]]}, {"Country": "Guinea-Bissau", "Confirmed": 1842, "Deaths": 26, "Recovered": 773, "Active": 1043, "Date": "2020-07-13T00:00:00Z", "ISO": "GW", "Geometry": [[-16.0, 12.0], [-15.0, 11.0], [-15.0, 12.0], [-14.0, 12.0]]}, {"Country": "Guinea-Bissau", "Confirmed": 1842, "Deaths": 26, "Recovered": 773, "Active": 1043, "Date": "2020-07-14T00:00:00Z", "ISO": "GW", "Geometry": [[-16.0, 12.0], [-15.0, 11.0], [-15.0, 12.0], [-14.0, 12.0]]}, {"Country": "Guinea-Bissau", "Confirmed": 1842, "Deaths": 26, "Recovered": 773, "Active": 1043, "Date": "2020-07-15T00:00:00Z", "ISO": "GW", "Geometry": [[-16.0, 12.0], [-15.0, 11.0], [-15.0, 12.0], [-14.0, 12.0]]}, {"Country": "Guinea-Bissau", "Confirmed": 1902, "Deaths": 26, "Recovered": 773, "Active": 1103, "Date": "2020-07-16T00:00:00Z", "ISO": "GW", "Geometry": [[-16.0, 12.0], [-15.0, 11.0], [-15.0, 12.0], [-14.0, 12.0]]}, {"Country": "Guinea-Bissau", "Confirmed": 1927, "Deaths": 26, "Recovered": 773, "Active": 1128, "Date": "2020-07-17T00:00:00Z", "ISO": "GW", "Geometry": [[-16.0, 12.0], [-15.0, 11.0], [-15.0, 12.0], [-14.0, 12.0]]}, {"Country": "Guinea-Bissau", "Confirmed": 1949, "Deaths": 26, "Recovered": 803, "Active": 1120, "Date": "2020-07-18T00:00:00Z", "ISO": "GW", "Geometry": [[-16.0, 12.0], [-15.0, 11.0], [-15.0, 12.0], [-14.0, 12.0]]}, {"Country": "Guinea-Bissau", "Confirmed": 1949, "Deaths": 26, "Recovered": 803, "Active": 1120, "Date": "2020-07-19T00:00:00Z", "ISO": "GW", "Geometry": [[-16.0, 12.0], [-15.0, 11.0], [-15.0, 12.0], [-14.0, 12.0]]}, {"Country": "Guinea-Bissau", "Confirmed": 1949, "Deaths": 26, "Recovered": 803, "Active": 1120, "Date": "2020-07-20T00:00:00Z", "ISO": "GW", "Geometry": [[-16.0, 12.0], [-15.0, 11.0], [-15.0, 12.0], [-14.0, 12.0]]}, {"Country": "Guinea-Bissau", "Confirmed": 1954, "Deaths": 26, "Recovered": 803, "Active": 1125, "Date": "2020-07-21T00:00:00Z", "ISO": "GW", "Geometry": [[-16.0, 12.0], [-15.0, 11.0], [-15.0, 12.0], [-14.0, 12.0]]}, {"Country": "Guinea-Bissau", "Confirmed": 1954, "Deaths": 26, "Recovered": 803, "Active": 1125, "Date": "2020-07-22T00:00:00Z", "ISO": "GW", "Geometry": [[-16.0, 12.0], [-15.0, 11.0], [-15.0, 12.0], [-14.0, 12.0]]}, {"Country": "Guinea-Bissau", "Confirmed": 1954, "Deaths": 26, "Recovered": 803, "Active": 1125, "Date": "2020-07-23T00:00:00Z", "ISO": "GW", "Geometry": [[-16.0, 12.0], [-15.0, 11.0], [-15.0, 12.0], [-14.0, 12.0]]}, {"Country": "Guinea-Bissau", "Confirmed": 1954, "Deaths": 26, "Recovered": 803, "Active": 1125, "Date": "2020-07-24T00:00:00Z", "ISO": "GW", "Geometry": [[-16.0, 12.0], [-15.0, 11.0], [-15.0, 12.0], [-14.0, 12.0]]}, {"Country": "Guinea-Bissau", "Confirmed": 1954, "Deaths": 26, "Recovered": 803, "Active": 1125, "Date": "2020-07-25T00:00:00Z", "ISO": "GW", "Geometry": [[-16.0, 12.0], [-15.0, 11.0], [-15.0, 12.0], [-14.0, 12.0]]}, {"Country": "Guinea-Bissau", "Confirmed": 1954, "Deaths": 26, "Recovered": 803, "Active": 1125, "Date": "2020-07-26T00:00:00Z", "ISO": "GW", "Geometry": [[-16.0, 12.0], [-15.0, 11.0], [-15.0, 12.0], [-14.0, 12.0]]}, {"Country": "Guinea-Bissau", "Confirmed": 1954, "Deaths": 26, "Recovered": 803, "Active": 1125, "Date": "2020-07-27T00:00:00Z", "ISO": "GW", "Geometry": [[-16.0, 12.0], [-15.0, 11.0], [-15.0, 12.0], [-14.0, 12.0]]}, {"Country": "Guinea-Bissau", "Confirmed": 1954, "Deaths": 26, "Recovered": 803, "Active": 1125, "Date": "2020-07-28T00:00:00Z", "ISO": "GW", "Geometry": [[-16.0, 12.0], [-15.0, 11.0], [-15.0, 12.0], [-14.0, 12.0]]}, {"Country": "Guinea-Bissau", "Confirmed": 1954, "Deaths": 26, "Recovered": 803, "Active": 1125, "Date": "2020-07-29T00:00:00Z", "ISO": "GW", "Geometry": [[-16.0, 12.0], [-15.0, 11.0], [-15.0, 12.0], [-14.0, 12.0]]}, {"Country": "Guinea-Bissau", "Confirmed": 1981, "Deaths": 26, "Recovered": 803, "Active": 1152, "Date": "2020-07-30T00:00:00Z", "ISO": "GW", "Geometry": [[-16.0, 12.0], [-15.0, 11.0], [-15.0, 12.0], [-14.0, 12.0]]}, {"Country": "Guinea-Bissau", "Confirmed": 1981, "Deaths": 26, "Recovered": 803, "Active": 1152, "Date": "2020-07-31T00:00:00Z", "ISO": "GW", "Geometry": [[-16.0, 12.0], [-15.0, 11.0], [-15.0, 12.0], [-14.0, 12.0]]}, {"Country": "Guinea-Bissau", "Confirmed": 1981, "Deaths": 27, "Recovered": 803, "Active": 1151, "Date": "2020-08-01T00:00:00Z", "ISO": "GW", "Geometry": [[-16.0, 12.0], [-15.0, 11.0], [-15.0, 12.0], [-14.0, 12.0]]}, {"Country": "Guinea-Bissau", "Confirmed": 1981, "Deaths": 27, "Recovered": 803, "Active": 1151, "Date": "2020-08-02T00:00:00Z", "ISO": "GW", "Geometry": [[-16.0, 12.0], [-15.0, 11.0], [-15.0, 12.0], [-14.0, 12.0]]}, {"Country": "Guinea-Bissau", "Confirmed": 1981, "Deaths": 27, "Recovered": 803, "Active": 1151, "Date": "2020-08-03T00:00:00Z", "ISO": "GW", "Geometry": [[-16.0, 12.0], [-15.0, 11.0], [-15.0, 12.0], [-14.0, 12.0]]}, {"Country": "Guinea-Bissau", "Confirmed": 1981, "Deaths": 27, "Recovered": 803, "Active": 1151, "Date": "2020-08-04T00:00:00Z", "ISO": "GW", "Geometry": [[-16.0, 12.0], [-15.0, 11.0], [-15.0, 12.0], [-14.0, 12.0]]}, {"Country": "Guinea-Bissau", "Confirmed": 2032, "Deaths": 27, "Recovered": 944, "Active": 1061, "Date": "2020-08-05T00:00:00Z", "ISO": "GW", "Geometry": [[-16.0, 12.0], [-15.0, 11.0], [-15.0, 12.0], [-14.0, 12.0]]}, {"Country": "Guinea-Bissau", "Confirmed": 2032, "Deaths": 27, "Recovered": 944, "Active": 1061, "Date": "2020-08-06T00:00:00Z", "ISO": "GW", "Geometry": [[-16.0, 12.0], [-15.0, 11.0], [-15.0, 12.0], [-14.0, 12.0]]}, {"Country": "Guinea-Bissau", "Confirmed": 2032, "Deaths": 27, "Recovered": 944, "Active": 1061, "Date": "2020-08-07T00:00:00Z", "ISO": "GW", "Geometry": [[-16.0, 12.0], [-15.0, 11.0], [-15.0, 12.0], [-14.0, 12.0]]}, {"Country": "Guinea-Bissau", "Confirmed": 2052, "Deaths": 29, "Recovered": 944, "Active": 1079, "Date": "2020-08-08T00:00:00Z", "ISO": "GW", "Geometry": [[-16.0, 12.0], [-15.0, 11.0], [-15.0, 12.0], [-14.0, 12.0]]}, {"Country": "Guinea-Bissau", "Confirmed": 2052, "Deaths": 29, "Recovered": 944, "Active": 1079, "Date": "2020-08-09T00:00:00Z", "ISO": "GW", "Geometry": [[-16.0, 12.0], [-15.0, 11.0], [-15.0, 12.0], [-14.0, 12.0]]}, {"Country": "Guinea-Bissau", "Confirmed": 2052, "Deaths": 29, "Recovered": 944, "Active": 1079, "Date": "2020-08-10T00:00:00Z", "ISO": "GW", "Geometry": [[-16.0, 12.0], [-15.0, 11.0], [-15.0, 12.0], [-14.0, 12.0]]}, {"Country": "Guinea-Bissau", "Confirmed": 2088, "Deaths": 29, "Recovered": 1015, "Active": 1044, "Date": "2020-08-11T00:00:00Z", "ISO": "GW", "Geometry": [[-16.0, 12.0], [-15.0, 11.0], [-15.0, 12.0], [-14.0, 12.0]]}, {"Country": "Guinea-Bissau", "Confirmed": 2088, "Deaths": 29, "Recovered": 1015, "Active": 1044, "Date": "2020-08-12T00:00:00Z", "ISO": "GW", "Geometry": [[-16.0, 12.0], [-15.0, 11.0], [-15.0, 12.0], [-14.0, 12.0]]}, {"Country": "Guinea-Bissau", "Confirmed": 2088, "Deaths": 29, "Recovered": 1015, "Active": 1044, "Date": "2020-08-13T00:00:00Z", "ISO": "GW", "Geometry": [[-16.0, 12.0], [-15.0, 11.0], [-15.0, 12.0], [-14.0, 12.0]]}, {"Country": "Guinea-Bissau", "Confirmed": 2088, "Deaths": 29, "Recovered": 1015, "Active": 1044, "Date": "2020-08-14T00:00:00Z", "ISO": "GW", "Geometry": [[-16.0, 12.0], [-15.0, 11.0], [-15.0, 12.0], [-14.0, 12.0]]}, {"Country": "Guinea-Bissau", "Confirmed": 2117, "Deaths": 33, "Recovered": 1015, "Active": 1069, "Date": "2020-08-15T00:00:00Z", "ISO": "GW", "Geometry": [[-16.0, 12.0], [-15.0, 11.0], [-15.0, 12.0], [-14.0, 12.0]]}, {"Country": "Guinea-Bissau", "Confirmed": 2117, "Deaths": 33, "Recovered": 1015, "Active": 1069, "Date": "2020-08-16T00:00:00Z", "ISO": "GW", "Geometry": [[-16.0, 12.0], [-15.0, 11.0], [-15.0, 12.0], [-14.0, 12.0]]}, {"Country": "Guinea-Bissau", "Confirmed": 2117, "Deaths": 33, "Recovered": 1015, "Active": 1069, "Date": "2020-08-17T00:00:00Z", "ISO": "GW", "Geometry": [[-16.0, 12.0], [-15.0, 11.0], [-15.0, 12.0], [-14.0, 12.0]]}, {"Country": "Guinea-Bissau", "Confirmed": 2117, "Deaths": 33, "Recovered": 1015, "Active": 1069, "Date": "2020-08-18T00:00:00Z", "ISO": "GW", "Geometry": [[-16.0, 12.0], [-15.0, 11.0], [-15.0, 12.0], [-14.0, 12.0]]}, {"Country": "Guinea-Bissau", "Confirmed": 2117, "Deaths": 33, "Recovered": 1015, "Active": 1069, "Date": "2020-08-19T00:00:00Z", "ISO": "GW", "Geometry": [[-16.0, 12.0], [-15.0, 11.0], [-15.0, 12.0], [-14.0, 12.0]]}, {"Country": "Guinea-Bissau", "Confirmed": 2149, "Deaths": 33, "Recovered": 1015, "Active": 1101, "Date": "2020-08-20T00:00:00Z", "ISO": "GW", "Geometry": [[-16.0, 12.0], [-15.0, 11.0], [-15.0, 12.0], [-14.0, 12.0]]}, {"Country": "Guinea-Bissau", "Confirmed": 2149, "Deaths": 33, "Recovered": 1015, "Active": 1101, "Date": "2020-08-21T00:00:00Z", "ISO": "GW", "Geometry": [[-16.0, 12.0], [-15.0, 11.0], [-15.0, 12.0], [-14.0, 12.0]]}, {"Country": "Guinea-Bissau", "Confirmed": 2149, "Deaths": 33, "Recovered": 1015, "Active": 1101, "Date": "2020-08-22T00:00:00Z", "ISO": "GW", "Geometry": [[-16.0, 12.0], [-15.0, 11.0], [-15.0, 12.0], [-14.0, 12.0]]}, {"Country": "Guinea-Bissau", "Confirmed": 2149, "Deaths": 33, "Recovered": 1015, "Active": 1101, "Date": "2020-08-23T00:00:00Z", "ISO": "GW", "Geometry": [[-16.0, 12.0], [-15.0, 11.0], [-15.0, 12.0], [-14.0, 12.0]]}, {"Country": "Guinea-Bissau", "Confirmed": 2149, "Deaths": 33, "Recovered": 1015, "Active": 1101, "Date": "2020-08-24T00:00:00Z", "ISO": "GW", "Geometry": [[-16.0, 12.0], [-15.0, 11.0], [-15.0, 12.0], [-14.0, 12.0]]}, {"Country": "Guinea-Bissau", "Confirmed": 2149, "Deaths": 33, "Recovered": 1015, "Active": 1101, "Date": "2020-08-25T00:00:00Z", "ISO": "GW", "Geometry": [[-16.0, 12.0], [-15.0, 11.0], [-15.0, 12.0], [-14.0, 12.0]]}, {"Country": "Guinea-Bissau", "Confirmed": 2205, "Deaths": 34, "Recovered": 1127, "Active": 1044, "Date": "2020-08-26T00:00:00Z", "ISO": "GW", "Geometry": [[-16.0, 12.0], [-15.0, 11.0], [-15.0, 12.0], [-14.0, 12.0]]}, {"Country": "Guinea-Bissau", "Confirmed": 2205, "Deaths": 34, "Recovered": 1127, "Active": 1044, "Date": "2020-08-27T00:00:00Z", "ISO": "GW", "Geometry": [[-16.0, 12.0], [-15.0, 11.0], [-15.0, 12.0], [-14.0, 12.0]]}, {"Country": "Guinea-Bissau", "Confirmed": 2205, "Deaths": 34, "Recovered": 1127, "Active": 1044, "Date": "2020-08-28T00:00:00Z", "ISO": "GW", "Geometry": [[-16.0, 12.0], [-15.0, 11.0], [-15.0, 12.0], [-14.0, 12.0]]}, {"Country": "Guinea-Bissau", "Confirmed": 2205, "Deaths": 34, "Recovered": 1127, "Active": 1044, "Date": "2020-08-29T00:00:00Z", "ISO": "GW", "Geometry": [[-16.0, 12.0], [-15.0, 11.0], [-15.0, 12.0], [-14.0, 12.0]]}, {"Country": "Guinea-Bissau", "Confirmed": 2205, "Deaths": 34, "Recovered": 1127, "Active": 1044, "Date": "2020-08-30T00:00:00Z", "ISO": "GW", "Geometry": [[-16.0, 12.0], [-15.0, 11.0], [-15.0, 12.0], [-14.0, 12.0]]}, {"Country": "Guinea-Bissau", "Confirmed": 2205, "Deaths": 34, "Recovered": 1127, "Active": 1044, "Date": "2020-08-31T00:00:00Z", "ISO": "GW", "Geometry": [[-16.0, 12.0], [-15.0, 11.0], [-15.0, 12.0], [-14.0, 12.0]]}, {"Country": "Guinea-Bissau", "Confirmed": 2205, "Deaths": 34, "Recovered": 1127, "Active": 1044, "Date": "2020-09-01T00:00:00Z", "ISO": "GW", "Geometry": [[-16.0, 12.0], [-15.0, 11.0], [-15.0, 12.0], [-14.0, 12.0]]}, {"Country": "Guinea-Bissau", "Confirmed": 2205, "Deaths": 34, "Recovered": 1127, "Active": 1044, "Date": "2020-09-02T00:00:00Z", "ISO": "GW", "Geometry": [[-16.0, 12.0], [-15.0, 11.0], [-15.0, 12.0], [-14.0, 12.0]]}, {"Country": "Guinea-Bissau", "Confirmed": 2205, "Deaths": 34, "Recovered": 1127, "Active": 1044, "Date": "2020-09-03T00:00:00Z", "ISO": "GW", "Geometry": [[-16.0, 12.0], [-15.0, 11.0], [-15.0, 12.0], [-14.0, 12.0]]}, {"Country": "Guinea-Bissau", "Confirmed": 2245, "Deaths": 38, "Recovered": 1127, "Active": 1080, "Date": "2020-09-04T00:00:00Z", "ISO": "GW", "Geometry": [[-16.0, 12.0], [-15.0, 11.0], [-15.0, 12.0], [-14.0, 12.0]]}, {"Country": "Guinea-Bissau", "Confirmed": 2245, "Deaths": 38, "Recovered": 1127, "Active": 1080, "Date": "2020-09-05T00:00:00Z", "ISO": "GW", "Geometry": [[-16.0, 12.0], [-15.0, 11.0], [-15.0, 12.0], [-14.0, 12.0]]}, {"Country": "Guinea-Bissau", "Confirmed": 2245, "Deaths": 38, "Recovered": 1127, "Active": 1080, "Date": "2020-09-06T00:00:00Z", "ISO": "GW", "Geometry": [[-16.0, 12.0], [-15.0, 11.0], [-15.0, 12.0], [-14.0, 12.0]]}, {"Country": "Guinea-Bissau", "Confirmed": 2245, "Deaths": 38, "Recovered": 1127, "Active": 1080, "Date": "2020-09-07T00:00:00Z", "ISO": "GW", "Geometry": [[-16.0, 12.0], [-15.0, 11.0], [-15.0, 12.0], [-14.0, 12.0]]}, {"Country": "Guinea-Bissau", "Confirmed": 2245, "Deaths": 38, "Recovered": 1127, "Active": 1080, "Date": "2020-09-08T00:00:00Z", "ISO": "GW", "Geometry": [[-16.0, 12.0], [-15.0, 11.0], [-15.0, 12.0], [-14.0, 12.0]]}, {"Country": "Guinea-Bissau", "Confirmed": 2245, "Deaths": 38, "Recovered": 1127, "Active": 1080, "Date": "2020-09-09T00:00:00Z", "ISO": "GW", "Geometry": [[-16.0, 12.0], [-15.0, 11.0], [-15.0, 12.0], [-14.0, 12.0]]}, {"Country": "Guinea-Bissau", "Confirmed": 2275, "Deaths": 39, "Recovered": 1127, "Active": 1109, "Date": "2020-09-10T00:00:00Z", "ISO": "GW", "Geometry": [[-16.0, 12.0], [-15.0, 11.0], [-15.0, 12.0], [-14.0, 12.0]]}, {"Country": "Guinea-Bissau", "Confirmed": 2275, "Deaths": 39, "Recovered": 1127, "Active": 1109, "Date": "2020-09-11T00:00:00Z", "ISO": "GW", "Geometry": [[-16.0, 12.0], [-15.0, 11.0], [-15.0, 12.0], [-14.0, 12.0]]}, {"Country": "Guinea-Bissau", "Confirmed": 2275, "Deaths": 39, "Recovered": 1127, "Active": 1109, "Date": "2020-09-12T00:00:00Z", "ISO": "GW", "Geometry": [[-16.0, 12.0], [-15.0, 11.0], [-15.0, 12.0], [-14.0, 12.0]]}, {"Country": "Guinea-Bissau", "Confirmed": 2275, "Deaths": 39, "Recovered": 1127, "Active": 1109, "Date": "2020-09-13T00:00:00Z", "ISO": "GW", "Geometry": [[-16.0, 12.0], [-15.0, 11.0], [-15.0, 12.0], [-14.0, 12.0]]}, {"Country": "Guinea-Bissau", "Confirmed": 2275, "Deaths": 39, "Recovered": 1127, "Active": 1109, "Date": "2020-09-14T00:00:00Z", "ISO": "GW", "Geometry": [[-16.0, 12.0], [-15.0, 11.0], [-15.0, 12.0], [-14.0, 12.0]]}, {"Country": "Guinea-Bissau", "Confirmed": 2275, "Deaths": 39, "Recovered": 1127, "Active": 1109, "Date": "2020-09-15T00:00:00Z", "ISO": "GW", "Geometry": [[-16.0, 12.0], [-15.0, 11.0], [-15.0, 12.0], [-14.0, 12.0]]}, {"Country": "Guinea-Bissau", "Confirmed": 2275, "Deaths": 39, "Recovered": 1127, "Active": 1109, "Date": "2020-09-16T00:00:00Z", "ISO": "GW", "Geometry": [[-16.0, 12.0], [-15.0, 11.0], [-15.0, 12.0], [-14.0, 12.0]]}, {"Country": "Guinea-Bissau", "Confirmed": 2275, "Deaths": 39, "Recovered": 1127, "Active": 1109, "Date": "2020-09-17T00:00:00Z", "ISO": "GW", "Geometry": [[-16.0, 12.0], [-15.0, 11.0], [-15.0, 12.0], [-14.0, 12.0]]}, {"Country": "Guinea-Bissau", "Confirmed": 2303, "Deaths": 39, "Recovered": 1127, "Active": 1137, "Date": "2020-09-18T00:00:00Z", "ISO": "GW", "Geometry": [[-16.0, 12.0], [-15.0, 11.0], [-15.0, 12.0], [-14.0, 12.0]]}, {"Country": "Guinea-Bissau", "Confirmed": 2303, "Deaths": 39, "Recovered": 1127, "Active": 1137, "Date": "2020-09-19T00:00:00Z", "ISO": "GW", "Geometry": [[-16.0, 12.0], [-15.0, 11.0], [-15.0, 12.0], [-14.0, 12.0]]}, {"Country": "Guinea-Bissau", "Confirmed": 2303, "Deaths": 39, "Recovered": 1127, "Active": 1137, "Date": "2020-09-20T00:00:00Z", "ISO": "GW", "Geometry": [[-16.0, 12.0], [-15.0, 11.0], [-15.0, 12.0], [-14.0, 12.0]]}, {"Country": "Guinea-Bissau", "Confirmed": 2303, "Deaths": 39, "Recovered": 1127, "Active": 1137, "Date": "2020-09-21T00:00:00Z", "ISO": "GW", "Geometry": [[-16.0, 12.0], [-15.0, 11.0], [-15.0, 12.0], [-14.0, 12.0]]}, {"Country": "Guinea-Bissau", "Confirmed": 2324, "Deaths": 39, "Recovered": 1549, "Active": 736, "Date": "2020-09-22T00:00:00Z", "ISO": "GW", "Geometry": [[-16.0, 12.0], [-15.0, 11.0], [-15.0, 12.0], [-14.0, 12.0]]}, {"Country": "Guinea-Bissau", "Confirmed": 2324, "Deaths": 39, "Recovered": 1549, "Active": 736, "Date": "2020-09-23T00:00:00Z", "ISO": "GW", "Geometry": [[-16.0, 12.0], [-15.0, 11.0], [-15.0, 12.0], [-14.0, 12.0]]}, {"Country": "Guinea-Bissau", "Confirmed": 2324, "Deaths": 39, "Recovered": 1549, "Active": 736, "Date": "2020-09-24T00:00:00Z", "ISO": "GW", "Geometry": [[-16.0, 12.0], [-15.0, 11.0], [-15.0, 12.0], [-14.0, 12.0]]}, {"Country": "Guinea-Bissau", "Confirmed": 2324, "Deaths": 39, "Recovered": 1549, "Active": 736, "Date": "2020-09-25T00:00:00Z", "ISO": "GW", "Geometry": [[-16.0, 12.0], [-15.0, 11.0], [-15.0, 12.0], [-14.0, 12.0]]}, {"Country": "Guinea-Bissau", "Confirmed": 2324, "Deaths": 39, "Recovered": 1549, "Active": 736, "Date": "2020-09-26T00:00:00Z", "ISO": "GW", "Geometry": [[-16.0, 12.0], [-15.0, 11.0], [-15.0, 12.0], [-14.0, 12.0]]}, {"Country": "Guinea-Bissau", "Confirmed": 2324, "Deaths": 39, "Recovered": 1549, "Active": 736, "Date": "2020-09-27T00:00:00Z", "ISO": "GW", "Geometry": [[-16.0, 12.0], [-15.0, 11.0], [-15.0, 12.0], [-14.0, 12.0]]}, {"Country": "Guinea-Bissau", "Confirmed": 2324, "Deaths": 39, "Recovered": 1549, "Active": 736, "Date": "2020-09-28T00:00:00Z", "ISO": "GW", "Geometry": [[-16.0, 12.0], [-15.0, 11.0], [-15.0, 12.0], [-14.0, 12.0]]}, {"Country": "Guinea-Bissau", "Confirmed": 2324, "Deaths": 39, "Recovered": 1549, "Active": 736, "Date": "2020-09-29T00:00:00Z", "ISO": "GW", "Geometry": [[-16.0, 12.0], [-15.0, 11.0], [-15.0, 12.0], [-14.0, 12.0]]}, {"Country": "Guinea-Bissau", "Confirmed": 2324, "Deaths": 39, "Recovered": 1549, "Active": 736, "Date": "2020-09-30T00:00:00Z", "ISO": "GW", "Geometry": [[-16.0, 12.0], [-15.0, 11.0], [-15.0, 12.0], [-14.0, 12.0]]}, {"Country": "Guinea-Bissau", "Confirmed": 2324, "Deaths": 39, "Recovered": 1549, "Active": 736, "Date": "2020-10-01T00:00:00Z", "ISO": "GW", "Geometry": [[-16.0, 12.0], [-15.0, 11.0], [-15.0, 12.0], [-14.0, 12.0]]}, {"Country": "Guinea-Bissau", "Confirmed": 2362, "Deaths": 39, "Recovered": 1549, "Active": 774, "Date": "2020-10-02T00:00:00Z", "ISO": "GW", "Geometry": [[-16.0, 12.0], [-15.0, 11.0], [-15.0, 12.0], [-14.0, 12.0]]}, {"Country": "Guinea-Bissau", "Confirmed": 2362, "Deaths": 39, "Recovered": 1549, "Active": 774, "Date": "2020-10-03T00:00:00Z", "ISO": "GW", "Geometry": [[-16.0, 12.0], [-15.0, 11.0], [-15.0, 12.0], [-14.0, 12.0]]}, {"Country": "Guinea-Bissau", "Confirmed": 2362, "Deaths": 39, "Recovered": 1549, "Active": 774, "Date": "2020-10-04T00:00:00Z", "ISO": "GW", "Geometry": [[-16.0, 12.0], [-15.0, 11.0], [-15.0, 12.0], [-14.0, 12.0]]}, {"Country": "Guinea-Bissau", "Confirmed": 2385, "Deaths": 40, "Recovered": 1728, "Active": 617, "Date": "2020-10-05T00:00:00Z", "ISO": "GW", "Geometry": [[-16.0, 12.0], [-15.0, 11.0], [-15.0, 12.0], [-14.0, 12.0]]}, {"Country": "Guinea-Bissau", "Confirmed": 2385, "Deaths": 40, "Recovered": 1728, "Active": 617, "Date": "2020-10-06T00:00:00Z", "ISO": "GW", "Geometry": [[-16.0, 12.0], [-15.0, 11.0], [-15.0, 12.0], [-14.0, 12.0]]}, {"Country": "Guinea-Bissau", "Confirmed": 2385, "Deaths": 40, "Recovered": 1728, "Active": 617, "Date": "2020-10-07T00:00:00Z", "ISO": "GW", "Geometry": [[-16.0, 12.0], [-15.0, 11.0], [-15.0, 12.0], [-14.0, 12.0]]}, {"Country": "Guinea-Bissau", "Confirmed": 2385, "Deaths": 40, "Recovered": 1728, "Active": 617, "Date": "2020-10-08T00:00:00Z", "ISO": "GW", "Geometry": [[-16.0, 12.0], [-15.0, 11.0], [-15.0, 12.0], [-14.0, 12.0]]}, {"Country": "Guinea-Bissau", "Confirmed": 2385, "Deaths": 40, "Recovered": 1728, "Active": 617, "Date": "2020-10-09T00:00:00Z", "ISO": "GW", "Geometry": [[-16.0, 12.0], [-15.0, 11.0], [-15.0, 12.0], [-14.0, 12.0]]}, {"Country": "Guinea-Bissau", "Confirmed": 2385, "Deaths": 40, "Recovered": 1728, "Active": 617, "Date": "2020-10-10T00:00:00Z", "ISO": "GW", "Geometry": [[-16.0, 12.0], [-15.0, 11.0], [-15.0, 12.0], [-14.0, 12.0]]}, {"Country": "Guinea-Bissau", "Confirmed": 2385, "Deaths": 40, "Recovered": 1728, "Active": 617, "Date": "2020-10-11T00:00:00Z", "ISO": "GW", "Geometry": [[-16.0, 12.0], [-15.0, 11.0], [-15.0, 12.0], [-14.0, 12.0]]}, {"Country": "Guinea-Bissau", "Confirmed": 2389, "Deaths": 41, "Recovered": 1782, "Active": 566, "Date": "2020-10-12T00:00:00Z", "ISO": "GW", "Geometry": [[-16.0, 12.0], [-15.0, 11.0], [-15.0, 12.0], [-14.0, 12.0]]}, {"Country": "Guinea-Bissau", "Confirmed": 2389, "Deaths": 41, "Recovered": 1782, "Active": 566, "Date": "2020-10-13T00:00:00Z", "ISO": "GW", "Geometry": [[-16.0, 12.0], [-15.0, 11.0], [-15.0, 12.0], [-14.0, 12.0]]}, {"Country": "Guinea-Bissau", "Confirmed": 2389, "Deaths": 41, "Recovered": 1782, "Active": 566, "Date": "2020-10-14T00:00:00Z", "ISO": "GW", "Geometry": [[-16.0, 12.0], [-15.0, 11.0], [-15.0, 12.0], [-14.0, 12.0]]}, {"Country": "Guinea-Bissau", "Confirmed": 2389, "Deaths": 41, "Recovered": 1782, "Active": 566, "Date": "2020-10-15T00:00:00Z", "ISO": "GW", "Geometry": [[-16.0, 12.0], [-15.0, 11.0], [-15.0, 12.0], [-14.0, 12.0]]}, {"Country": "Guinea-Bissau", "Confirmed": 2389, "Deaths": 41, "Recovered": 1782, "Active": 566, "Date": "2020-10-16T00:00:00Z", "ISO": "GW", "Geometry": [[-16.0, 12.0], [-15.0, 11.0], [-15.0, 12.0], [-14.0, 12.0]]}, {"Country": "Guinea-Bissau", "Confirmed": 2389, "Deaths": 41, "Recovered": 1782, "Active": 566, "Date": "2020-10-17T00:00:00Z", "ISO": "GW", "Geometry": [[-16.0, 12.0], [-15.0, 11.0], [-15.0, 12.0], [-14.0, 12.0]]}, {"Country": "Guinea-Bissau", "Confirmed": 2389, "Deaths": 41, "Recovered": 1782, "Active": 566, "Date": "2020-10-18T00:00:00Z", "ISO": "GW", "Geometry": [[-16.0, 12.0], [-15.0, 11.0], [-15.0, 12.0], [-14.0, 12.0]]}, {"Country": "Guinea-Bissau", "Confirmed": 2403, "Deaths": 41, "Recovered": 1818, "Active": 544, "Date": "2020-10-19T00:00:00Z", "ISO": "GW", "Geometry": [[-16.0, 12.0], [-15.0, 11.0], [-15.0, 12.0], [-14.0, 12.0]]}, {"Country": "Guinea-Bissau", "Confirmed": 2403, "Deaths": 41, "Recovered": 1818, "Active": 544, "Date": "2020-10-20T00:00:00Z", "ISO": "GW", "Geometry": [[-16.0, 12.0], [-15.0, 11.0], [-15.0, 12.0], [-14.0, 12.0]]}, {"Country": "Guinea-Bissau", "Confirmed": 2403, "Deaths": 41, "Recovered": 1818, "Active": 544, "Date": "2020-10-21T00:00:00Z", "ISO": "GW", "Geometry": [[-16.0, 12.0], [-15.0, 11.0], [-15.0, 12.0], [-14.0, 12.0]]}, {"Country": "Guinea-Bissau", "Confirmed": 2403, "Deaths": 41, "Recovered": 1818, "Active": 544, "Date": "2020-10-22T00:00:00Z", "ISO": "GW", "Geometry": [[-16.0, 12.0], [-15.0, 11.0], [-15.0, 12.0], [-14.0, 12.0]]}, {"Country": "Guinea-Bissau", "Confirmed": 2403, "Deaths": 41, "Recovered": 1818, "Active": 544, "Date": "2020-10-23T00:00:00Z", "ISO": "GW", "Geometry": [[-16.0, 12.0], [-15.0, 11.0], [-15.0, 12.0], [-14.0, 12.0]]}, {"Country": "Guinea-Bissau", "Confirmed": 2403, "Deaths": 41, "Recovered": 1818, "Active": 544, "Date": "2020-10-24T00:00:00Z", "ISO": "GW", "Geometry": [[-16.0, 12.0], [-15.0, 11.0], [-15.0, 12.0], [-14.0, 12.0]]}, {"Country": "Guinea-Bissau", "Confirmed": 2403, "Deaths": 41, "Recovered": 1818, "Active": 544, "Date": "2020-10-25T00:00:00Z", "ISO": "GW", "Geometry": [[-16.0, 12.0], [-15.0, 11.0], [-15.0, 12.0], [-14.0, 12.0]]}, {"Country": "Guinea-Bissau", "Confirmed": 2403, "Deaths": 41, "Recovered": 1818, "Active": 544, "Date": "2020-10-26T00:00:00Z", "ISO": "GW", "Geometry": [[-16.0, 12.0], [-15.0, 11.0], [-15.0, 12.0], [-14.0, 12.0]]}, {"Country": "Guinea-Bissau", "Confirmed": 2403, "Deaths": 41, "Recovered": 1818, "Active": 544, "Date": "2020-10-27T00:00:00Z", "ISO": "GW", "Geometry": [[-16.0, 12.0], [-15.0, 11.0], [-15.0, 12.0], [-14.0, 12.0]]}, {"Country": "Guinea-Bissau", "Confirmed": 2403, "Deaths": 41, "Recovered": 1818, "Active": 544, "Date": "2020-10-28T00:00:00Z", "ISO": "GW", "Geometry": [[-16.0, 12.0], [-15.0, 11.0], [-15.0, 12.0], [-14.0, 12.0]]}, {"Country": "Guinea-Bissau", "Confirmed": 2403, "Deaths": 41, "Recovered": 1818, "Active": 544, "Date": "2020-10-29T00:00:00Z", "ISO": "GW", "Geometry": [[-16.0, 12.0], [-15.0, 11.0], [-15.0, 12.0], [-14.0, 12.0]]}, {"Country": "Guinea-Bissau", "Confirmed": 2403, "Deaths": 41, "Recovered": 1818, "Active": 544, "Date": "2020-10-30T00:00:00Z", "ISO": "GW", "Geometry": [[-16.0, 12.0], [-15.0, 11.0], [-15.0, 12.0], [-14.0, 12.0]]}, {"Country": "Guinea-Bissau", "Confirmed": 2413, "Deaths": 41, "Recovered": 1818, "Active": 554, "Date": "2020-10-31T00:00:00Z", "ISO": "GW", "Geometry": [[-16.0, 12.0], [-15.0, 11.0], [-15.0, 12.0], [-14.0, 12.0]]}, {"Country": "Guinea-Bissau", "Confirmed": 2413, "Deaths": 41, "Recovered": 1818, "Active": 554, "Date": "2020-11-01T00:00:00Z", "ISO": "GW", "Geometry": [[-16.0, 12.0], [-15.0, 11.0], [-15.0, 12.0], [-14.0, 12.0]]}, {"Country": "Guinea-Bissau", "Confirmed": 2413, "Deaths": 41, "Recovered": 1818, "Active": 554, "Date": "2020-11-02T00:00:00Z", "ISO": "GW", "Geometry": [[-16.0, 12.0], [-15.0, 11.0], [-15.0, 12.0], [-14.0, 12.0]]}, {"Country": "Guinea-Bissau", "Confirmed": 2413, "Deaths": 41, "Recovered": 1818, "Active": 554, "Date": "2020-11-03T00:00:00Z", "ISO": "GW", "Geometry": [[-16.0, 12.0], [-15.0, 11.0], [-15.0, 12.0], [-14.0, 12.0]]}, {"Country": "Guinea-Bissau", "Confirmed": 2414, "Deaths": 42, "Recovered": 1862, "Active": 510, "Date": "2020-11-04T00:00:00Z", "ISO": "GW", "Geometry": [[-16.0, 12.0], [-15.0, 11.0], [-15.0, 12.0], [-14.0, 12.0]]}, {"Country": "Guinea-Bissau", "Confirmed": 2414, "Deaths": 42, "Recovered": 1862, "Active": 510, "Date": "2020-11-05T00:00:00Z", "ISO": "GW", "Geometry": [[-16.0, 12.0], [-15.0, 11.0], [-15.0, 12.0], [-14.0, 12.0]]}, {"Country": "Guinea-Bissau", "Confirmed": 2414, "Deaths": 42, "Recovered": 1862, "Active": 510, "Date": "2020-11-06T00:00:00Z", "ISO": "GW", "Geometry": [[-16.0, 12.0], [-15.0, 11.0], [-15.0, 12.0], [-14.0, 12.0]]}, {"Country": "Guinea-Bissau", "Confirmed": 2414, "Deaths": 42, "Recovered": 1862, "Active": 510, "Date": "2020-11-07T00:00:00Z", "ISO": "GW", "Geometry": [[-16.0, 12.0], [-15.0, 11.0], [-15.0, 12.0], [-14.0, 12.0]]}, {"Country": "Guinea-Bissau", "Confirmed": 2414, "Deaths": 42, "Recovered": 1862, "Active": 510, "Date": "2020-11-08T00:00:00Z", "ISO": "GW", "Geometry": [[-16.0, 12.0], [-15.0, 11.0], [-15.0, 12.0], [-14.0, 12.0]]}, {"Country": "Guinea-Bissau", "Confirmed": 2419, "Deaths": 43, "Recovered": 2255, "Active": 121, "Date": "2020-11-09T00:00:00Z", "ISO": "GW", "Geometry": [[-16.0, 12.0], [-15.0, 11.0], [-15.0, 12.0], [-14.0, 12.0]]}, {"Country": "Guinea-Bissau", "Confirmed": 2419, "Deaths": 43, "Recovered": 2255, "Active": 121, "Date": "2020-11-10T00:00:00Z", "ISO": "GW", "Geometry": [[-16.0, 12.0], [-15.0, 11.0], [-15.0, 12.0], [-14.0, 12.0]]}, {"Country": "Guinea-Bissau", "Confirmed": 2419, "Deaths": 43, "Recovered": 2255, "Active": 121, "Date": "2020-11-11T00:00:00Z", "ISO": "GW", "Geometry": [[-16.0, 12.0], [-15.0, 11.0], [-15.0, 12.0], [-14.0, 12.0]]}, {"Country": "Guinea-Bissau", "Confirmed": 2419, "Deaths": 43, "Recovered": 2255, "Active": 121, "Date": "2020-11-12T00:00:00Z", "ISO": "GW", "Geometry": [[-16.0, 12.0], [-15.0, 11.0], [-15.0, 12.0], [-14.0, 12.0]]}, {"Country": "Guinea-Bissau", "Confirmed": 2419, "Deaths": 43, "Recovered": 2255, "Active": 121, "Date": "2020-11-13T00:00:00Z", "ISO": "GW", "Geometry": [[-16.0, 12.0], [-15.0, 11.0], [-15.0, 12.0], [-14.0, 12.0]]}, {"Country": "Guinea-Bissau", "Confirmed": 2419, "Deaths": 43, "Recovered": 2255, "Active": 121, "Date": "2020-11-14T00:00:00Z", "ISO": "GW", "Geometry": [[-16.0, 12.0], [-15.0, 11.0], [-15.0, 12.0], [-14.0, 12.0]]}, {"Country": "Guinea-Bissau", "Confirmed": 2419, "Deaths": 43, "Recovered": 2255, "Active": 121, "Date": "2020-11-15T00:00:00Z", "ISO": "GW", "Geometry": [[-16.0, 12.0], [-15.0, 11.0], [-15.0, 12.0], [-14.0, 12.0]]}, {"Country": "Guinea-Bissau", "Confirmed": 2419, "Deaths": 43, "Recovered": 2255, "Active": 121, "Date": "2020-11-16T00:00:00Z", "ISO": "GW", "Geometry": [[-16.0, 12.0], [-15.0, 11.0], [-15.0, 12.0], [-14.0, 12.0]]}, {"Country": "Guinea-Bissau", "Confirmed": 2419, "Deaths": 43, "Recovered": 2255, "Active": 121, "Date": "2020-11-17T00:00:00Z", "ISO": "GW", "Geometry": [[-16.0, 12.0], [-15.0, 11.0], [-15.0, 12.0], [-14.0, 12.0]]}, {"Country": "Guinea-Bissau", "Confirmed": 2421, "Deaths": 43, "Recovered": 2286, "Active": 92, "Date": "2020-11-18T00:00:00Z", "ISO": "GW", "Geometry": [[-16.0, 12.0], [-15.0, 11.0], [-15.0, 12.0], [-14.0, 12.0]]}, {"Country": "Guinea-Bissau", "Confirmed": 2421, "Deaths": 43, "Recovered": 2286, "Active": 92, "Date": "2020-11-19T00:00:00Z", "ISO": "GW", "Geometry": [[-16.0, 12.0], [-15.0, 11.0], [-15.0, 12.0], [-14.0, 12.0]]}, {"Country": "Guinea-Bissau", "Confirmed": 2421, "Deaths": 43, "Recovered": 2286, "Active": 92, "Date": "2020-11-20T00:00:00Z", "ISO": "GW", "Geometry": [[-16.0, 12.0], [-15.0, 11.0], [-15.0, 12.0], [-14.0, 12.0]]}, {"Country": "Guinea-Bissau", "Confirmed": 2421, "Deaths": 43, "Recovered": 2286, "Active": 92, "Date": "2020-11-21T00:00:00Z", "ISO": "GW", "Geometry": [[-16.0, 12.0], [-15.0, 11.0], [-15.0, 12.0], [-14.0, 12.0]]}, {"Country": "Guinea-Bissau", "Confirmed": 2421, "Deaths": 43, "Recovered": 2286, "Active": 92, "Date": "2020-11-22T00:00:00Z", "ISO": "GW", "Geometry": [[-16.0, 12.0], [-15.0, 11.0], [-15.0, 12.0], [-14.0, 12.0]]}, {"Country": "Guinea-Bissau", "Confirmed": 2422, "Deaths": 43, "Recovered": 2309, "Active": 70, "Date": "2020-11-23T00:00:00Z", "ISO": "GW", "Geometry": [[-16.0, 12.0], [-15.0, 11.0], [-15.0, 12.0], [-14.0, 12.0]]}, {"Country": "Guinea-Bissau", "Confirmed": 2422, "Deaths": 43, "Recovered": 2309, "Active": 70, "Date": "2020-11-24T00:00:00Z", "ISO": "GW", "Geometry": [[-16.0, 12.0], [-15.0, 11.0], [-15.0, 12.0], [-14.0, 12.0]]}, {"Country": "Guinea-Bissau", "Confirmed": 2422, "Deaths": 43, "Recovered": 2309, "Active": 70, "Date": "2020-11-25T00:00:00Z", "ISO": "GW", "Geometry": [[-16.0, 12.0], [-15.0, 11.0], [-15.0, 12.0], [-14.0, 12.0]]}, {"Country": "Guinea-Bissau", "Confirmed": 2422, "Deaths": 43, "Recovered": 2309, "Active": 70, "Date": "2020-11-26T00:00:00Z", "ISO": "GW", "Geometry": [[-16.0, 12.0], [-15.0, 11.0], [-15.0, 12.0], [-14.0, 12.0]]}, {"Country": "Guinea-Bissau", "Confirmed": 2422, "Deaths": 43, "Recovered": 2309, "Active": 70, "Date": "2020-11-27T00:00:00Z", "ISO": "GW", "Geometry": [[-16.0, 12.0], [-15.0, 11.0], [-15.0, 12.0], [-14.0, 12.0]]}, {"Country": "Guinea-Bissau", "Confirmed": 2422, "Deaths": 43, "Recovered": 2309, "Active": 70, "Date": "2020-11-28T00:00:00Z", "ISO": "GW", "Geometry": [[-16.0, 12.0], [-15.0, 11.0], [-15.0, 12.0], [-14.0, 12.0]]}, {"Country": "Guinea-Bissau", "Confirmed": 2422, "Deaths": 43, "Recovered": 2309, "Active": 70, "Date": "2020-11-29T00:00:00Z", "ISO": "GW", "Geometry": [[-16.0, 12.0], [-15.0, 11.0], [-15.0, 12.0], [-14.0, 12.0]]}, {"Country": "Guinea-Bissau", "Confirmed": 2441, "Deaths": 44, "Recovered": 2327, "Active": 70, "Date": "2020-11-30T00:00:00Z", "ISO": "GW", "Geometry": [[-16.0, 12.0], [-15.0, 11.0], [-15.0, 12.0], [-14.0, 12.0]]}, {"Country": "Guinea-Bissau", "Confirmed": 2441, "Deaths": 44, "Recovered": 2327, "Active": 70, "Date": "2020-12-01T00:00:00Z", "ISO": "GW", "Geometry": [[-16.0, 12.0], [-15.0, 11.0], [-15.0, 12.0], [-14.0, 12.0]]}, {"Country": "Guinea-Bissau", "Confirmed": 2441, "Deaths": 44, "Recovered": 2327, "Active": 70, "Date": "2020-12-02T00:00:00Z", "ISO": "GW", "Geometry": [[-16.0, 12.0], [-15.0, 11.0], [-15.0, 12.0], [-14.0, 12.0]]}, {"Country": "Guinea-Bissau", "Confirmed": 2441, "Deaths": 44, "Recovered": 2327, "Active": 70, "Date": "2020-12-03T00:00:00Z", "ISO": "GW", "Geometry": [[-16.0, 12.0], [-15.0, 11.0], [-15.0, 12.0], [-14.0, 12.0]]}, {"Country": "Guinea-Bissau", "Confirmed": 2441, "Deaths": 44, "Recovered": 2327, "Active": 70, "Date": "2020-12-04T00:00:00Z", "ISO": "GW", "Geometry": [[-16.0, 12.0], [-15.0, 11.0], [-15.0, 12.0], [-14.0, 12.0]]}, {"Country": "Guinea-Bissau", "Confirmed": 2441, "Deaths": 44, "Recovered": 2327, "Active": 70, "Date": "2020-12-05T00:00:00Z", "ISO": "GW", "Geometry": [[-16.0, 12.0], [-15.0, 11.0], [-15.0, 12.0], [-14.0, 12.0]]}]